LICENSE
MANIFEST.in
README.md
README.rst
setup.cfg
setup.py
djbrut/__init__.py
djbrut/checkers.py
djbrut/core.py
djbrut/default_settings.py
djbrut/settings.py
djbrut/utils.py
djbrut.egg-info/PKG-INFO
djbrut.egg-info/SOURCES.txt
djbrut.egg-info/dependency_links.txt
djbrut.egg-info/top_level.txt