Metadata-Version: 1.1
Name: djbrut
Version: 1.0.0
Summary: Framework for views in big projects on Django.
Home-page: https://github.com/orsinium/django-bruteforce-protection
Author: orsinium
Author-email: master_fess@mail.ru
License: GNU Lesser General Public License v3.0
Download-URL: https://github.com/orsinium/django-bruteforce-protection/tarball/master
Keywords: djbrut django bruteforce protection security redis
Platform: UNKNOWN
Classifier: Development Status :: 5 - Production/Stable
Classifier: Environment :: Plugins
Classifier: Framework :: Django
Classifier: Intended Audience :: Developers
Classifier: License :: OSI Approved :: GNU Lesser General Public License v3 or later (LGPLv3+)
Classifier: Programming Language :: Python
Requires: django
Requires: redis
